setup.cfg
setup.py
computer/__init__.py
computer/evaluate.py
computer/exceptions.py
computer/operations.py
computer.egg-info/PKG-INFO
computer.egg-info/SOURCES.txt
computer.egg-info/dependency_links.txt
computer.egg-info/top_level.txt